message_queueing.py
utils.py
conformance_testing/__init__.py
conformance_testing/test_errors.py
conformance_testing/test_step_sequence.py
conformance_testing/test_timer.py
conformance_testing/testingtool_messages.py
conformance_testing/testingtool_services.py
finterop/__init__.py
florawan_testing-1.1.2.dist-info/DESCRIPTION.rst
florawan_testing-1.1.2.dist-info/METADATA
florawan_testing-1.1.2.dist-info/RECORD
florawan_testing-1.1.2.dist-info/WHEEL
florawan_testing-1.1.2.dist-info/entry_points.txt
florawan_testing-1.1.2.dist-info/metadata.json
florawan_testing-1.1.2.dist-info/top_level.txt
lorawan/__init__.py
lorawan/lorawan_utils.py
lorawan/sessions.py
lorawan/lorawan_conformance/__init__.py
lorawan/lorawan_conformance/lorawan_errors.py
lorawan/lorawan_conformance/lorawan_steps.py
lorawan/lorawan_conformance/activation/__init__.py
lorawan/lorawan_conformance/activation/td_lorawan_act_01.py
lorawan/lorawan_conformance/activation/td_lorawan_act_02.py
lorawan/lorawan_conformance/activation/td_lorawan_act_03.py
lorawan/lorawan_conformance/activation/td_lorawan_act_04.py
lorawan/lorawan_conformance/activation/td_lorawan_act_05.py
lorawan/lorawan_conformance/functionality/__init__.py
lorawan/lorawan_conformance/functionality/fun_steps.py
lorawan/lorawan_conformance/functionality/td_lorawan_fun_01.py
lorawan/lorawan_conformance/functionality/td_lorawan_fun_02.py
lorawan/lorawan_conformance/functionality/td_lorawan_fun_03.py
lorawan/lorawan_conformance/functionality/td_lorawan_fun_04.py
lorawan/lorawan_conformance/functionality/td_lorawan_fun_05.py
lorawan/lorawan_conformance/functionality/td_lorawan_fun_06.py
lorawan/lorawan_conformance/general/__init__.py
lorawan/lorawan_conformance/general/td_lorawan_deactivate.py
lorawan/lorawan_conformance/general/td_lorawan_reset.py
lorawan/lorawan_conformance/mac_commands/__init__.py
lorawan/lorawan_conformance/mac_commands/mac_steps.py
lorawan/lorawan_conformance/mac_commands/td_lorawan_mac_01.py
lorawan/lorawan_conformance/mac_commands/td_lorawan_mac_02.py
lorawan/lorawan_conformance/mac_commands/td_lorawan_mac_03.py
lorawan/lorawan_conformance/mac_commands/td_lorawan_mac_04.py
lorawan/lorawan_conformance/mac_commands/td_lorawan_mac_05.py
lorawan/lorawan_conformance/security/__init__.py
