Metadata-Version: 2.0
Name: florawan-testing
Version: 1.1.2
Summary: F-LoRa LoRaWAN testing user Agent.
Home-page: UNKNOWN
Author: Pablo Modernell
Author-email: pablomodernell@gmail.com
License: UNKNOWN
Platform: UNKNOWN
Requires-Dist: click (==6.7)
Requires-Dist: pika (==0.12.0)
Requires-Dist: pycryptodomex (==3.6.6)
